chuidi_zipcode/__init__.py
chuidi_zipcode/engine.py
chuidi_zipcode/us_zipcodes.csv
chuidi_zipcode-0.1.0.dist-info/METADATA
chuidi_zipcode-0.1.0.dist-info/WHEEL
chuidi_zipcode-0.1.0.dist-info/top_level.txt
chuidi_zipcode-0.1.0.dist-info/RECORD
