Metadata-Version: 2.4
Name: chuidi_zipcode
Version: 0.1.0
Summary: A super zipcode lookup library based on GeoNames CSV
Author: chuidi
Requires-Python: >=3.7
Dynamic: author
Dynamic: description
Dynamic: requires-python
Dynamic: summary
